{
  "success": true,
  "resultObject": {
    "message": 0,
    "information": [
      {
        "id":"sdhfksdvzx354jhdsfjsd",
        "title": "就发给你快放寒假了就好了的所发生的个",
        "Read":true,
        "time": 635436546,
        "content": "的双丰收了的客户发动机可好看了的发挥领导是电饭锅和卢卡斯的韩国辣屌丝夫妇圣诞节过后看来是大家发过来"
      },{
        "id":"sdhfksdvzx354jhdsfjsd",
        "title": "就发给你快放寒假了就好了的所发生的个",
        "Read":true,
        "time": 635436546,
        "content": "的双丰收了的客户发动机可好看了的发挥领导是电饭锅和卢卡斯的韩国辣屌丝夫妇圣诞节过后看来是大家发过来"
      },{
        "id":"sdhfksdvzx354jhdsfjsd",
        "title": "就发给你快放寒假了就好了的所发生的个",
        "Read":true,
        "time": 635436546,
        "content": "的双丰收了的客户发动机可好看了的发挥领导是电饭锅和卢卡斯的韩国辣屌丝夫妇圣诞节过后看来是大家发过来"
      },{
        "id":"sdhfksdvzx354jhdsfjsd",
        "title": "就发给你快放寒假了就好了的所发生的个",
        "Read":true,
        "time": 635436546,
        "content": "的双丰收了的客户发动机可好看了的发挥领导是电饭锅和卢卡斯的韩国辣屌丝夫妇圣诞节过后看来是大家发过来"
      },{
        "id":"sdhfksdvzx354jhdsfjsd",
        "title": "就发给你快放寒假了就好了的所发生的个",
        "Read":true,
        "time": 635436546,
        "content": "的双丰收了的客户发动机可好看了的发挥领导是电饭锅和卢卡斯的韩国辣屌丝夫妇圣诞节过后看来是大家发过来"
      },{
        "id":"sdhfksdvzx354jhdsfjsd",
        "title": "就发给你快放寒假了就好了的所发生的个",
        "Read":true,
        "time": 635436546,
        "content": "的双丰收了的客户发动机可好看了的发挥领导是电饭锅和卢卡斯的韩国辣屌丝夫妇圣诞节过后看来是大家发过来"
      },{
        "id":"sdhfksdvzx354jhdsfjsd",
        "title": "就发给你快放寒假了就好了的所发生的个",
        "Read":true,
        "time": 635436546,
        "content": "的双丰收了的客户发动机可好看了的发挥领导是电饭锅和卢卡斯的韩国辣屌丝夫妇圣诞节过后看来是大家发过来"
      }
    ],
    "totalpages":100,
    "currentpage":1,
    "totalnumber": 1000
  }
}